telebit/__init__.py
telebit/exceptions.py
telebit/telebit.py
telebit_python-0.1.0.dist-info/LICENSE
telebit_python-0.1.0.dist-info/METADATA
telebit_python-0.1.0.dist-info/WHEEL
telebit_python-0.1.0.dist-info/top_level.txt
telebit_python-0.1.0.dist-info/RECORD
