Metadata-Version: 2.1
Name: telebit-python
Version: 0.1.0
Summary: A wrapper around telebit (ngrok like service).
Author: Xeroxxhah (Muhammad Nauman Azeem)
Author-email: xeroxxhah@pm.me
Keywords: python,python3,telebit,tunnel
License-File: LICENSE
